mcp_oracle_server/__init__.py
mcp_oracle_server/oracle_tools.py
mcp_oracle_server-1.0.1.dist-info/METADATA
mcp_oracle_server-1.0.1.dist-info/WHEEL
mcp_oracle_server-1.0.1.dist-info/entry_points.txt
mcp_oracle_server-1.0.1.dist-info/licenses/LICENSE
mcp_oracle_server-1.0.1.dist-info/RECORD
