Metadata-Version: 2.4
Name: mcp-oracle-server
Version: 1.0.1
Summary: Model Context Protocol server to access oracle database
Author-email: king <mr.zhen2011@gmail.com>
License-File: LICENSE
Requires-Python: >=3.12
Requires-Dist: mcp[cli]>=1.5.0
Requires-Dist: oracledb>=3.0.0
Requires-Dist: python-dotenv>=1.0.1
